gemini_pt/__init__.py
gemini_pt/ai_config.py
gemini_pt/install_util.py
gemini_pt/main.py
gemini_pt/prompt_webpen_v1.py
gemini_pt/report_creation.py
gemini_pt/session_management.py
gemini_pt/target_info.py
gemini_pt/task_execution.py
gemini_pt/utils.py
gemini_pt/tools/__init__.py
gemini_pt/tools/authorized_tools.txt
gemini_pt/tools/tool_priority.txt
gemini_pt-0.0.5.dist-info/METADATA
gemini_pt-0.0.5.dist-info/WHEEL
gemini_pt-0.0.5.dist-info/entry_points.txt
gemini_pt-0.0.5.dist-info/top_level.txt
gemini_pt-0.0.5.dist-info/RECORD
