Metadata-Version: 2.1
Name: gemini_pt
Version: 0.0.5
Summary: Automatic pentest using AI
Author: Elouan Teissere
Author-email: <elouan.teissere@sii.fr>
Project-URL: My github, https://github.com/Yellowwaves
Keywords: python,gemini,pentest,ai,cybersecurity,nmap
Classifier: Development Status :: 3 - Alpha
Classifier: Intended Audience :: Education
Classifier: Programming Language :: Python :: 3.9
Classifier: Operating System :: POSIX
Requires-Dist: google-generativeai
Requires-Dist: grpcio
Requires-Dist: markdown2
Requires-Dist: openai
Requires-Dist: pdfkit
Requires-Dist: python-dotenv
Requires-Dist: python-nmap
